AXX_AIAPI-1.3.0.data/data/.DS_Store
AXX_AIAPI-1.3.0.data/data/__init__.py
AXX_AIAPI-1.3.0.data/data/api.py
AXX_AIAPI-1.3.0.data/data/constants.py
AXX_AIAPI-1.3.0.data/data/db_demo.py
AXX_AIAPI-1.3.0.data/data/gunicorn.config.py
AXX_AIAPI-1.3.0.data/data/index.py
AXX_AIAPI-1.3.0.data/data/log_config.py
AXX_AIAPI-1.3.0.data/data/manage.py
AXX_AIAPI-1.3.0.data/data/requirements.txt
AXX_AIAPI-1.3.0.data/data/server.py
AXX_AIAPI-1.3.0.data/data/startserver.sh
AXX_AIAPI-1.3.0.data/data/stopserver.sh
axx_aiapp/__init__.py
axx_aiapp/templates/.DS_Store
axx_aiapp/templates/__init__.py
axx_aiapp/templates/project_template/.DS_Store
axx_aiapp/templates/project_template/project_name/.DS_Store
axx_aiapp/templates/project_template/project_name/manage.py
axx_aiapp/templates/project_template/project_name/requirements.txt
axx_aiapp/templates/project_template/project_name/server.py
axx_aiapp/templates/project_template/project_name/startserver.sh
axx_aiapp/templates/project_template/project_name/stopserver.sh
axx_aiapp/templates/project_template/project_name/common/__init__.py
axx_aiapp/templates/project_template/project_name/concurrent_log/__init__.py
axx_aiapp/templates/project_template/project_name/config/__init__.py
axx_aiapp/templates/project_template/project_name/config/gunicorn.config.py
axx_aiapp/templates/project_template/project_name/config/log_config.py
axx_aiapp/templates/project_template/project_name/controller/__init__.py
axx_aiapp/templates/project_template/project_name/controller/api.py
axx_aiapp/templates/project_template/project_name/controller/index.py
axx_aiapp/templates/project_template/project_name/db/__init__.py
axx_aiapp/templates/project_template/project_name/db/db_demo.py
axx_aiapp/templates/project_template/project_name/model/__init__.py
axx_aiapp/templates/project_template/project_name/service/__init__.py
axx_aiapp/templates/project_template/project_name/utils/__init__.py
axx_aiapp/templates/project_template/project_name/utils/constants.py
AXX_AIAPI-1.3.0.dist-info/LICENSE
AXX_AIAPI-1.3.0.dist-info/METADATA
AXX_AIAPI-1.3.0.dist-info/WHEEL
AXX_AIAPI-1.3.0.dist-info/entry_points.txt
AXX_AIAPI-1.3.0.dist-info/top_level.txt
AXX_AIAPI-1.3.0.dist-info/RECORD
