Metadata-Version: 2.1
Name: AXX-AIAPI
Version: 1.3.0
Summary: create application template for axx ai-api.
Home-page: UNKNOWN
Author: ZhenYu Dan
Author-email: ljqwzan@vip.qq.com
License: GUN V3
Keywords: AXX,axx,axx ai,axx aiapi
Platform: any
Classifier: Development Status :: 3 - Alpha
Classifier: Topic :: Utilities
Classifier: License :: OSI Approved :: GNU General Public License (GPL)
Requires-Dist: flask (>=1.0.2)
